__init__.py
mcp_veo3_azure_blob.py
mcp_veo3_azure_blob-1.0.17.dist-info/METADATA
mcp_veo3_azure_blob-1.0.17.dist-info/WHEEL
mcp_veo3_azure_blob-1.0.17.dist-info/entry_points.txt
mcp_veo3_azure_blob-1.0.17.dist-info/licenses/LICENSE
mcp_veo3_azure_blob-1.0.17.dist-info/RECORD
