Metadata-Version: 2.4
Name: mcp-veo3-azure-blob
Version: 1.0.17
Summary: MCP Veo 3 Video Generator - A Model Context Protocol server for Veo 3 video generation and Azure Blob Upload
Project-URL: Homepage, https://github.com/ctoicqtao/mcp-veo3-azure-blob
Project-URL: Repository, https://github.com/ctoicqtao/mcp-veo3-azure-blob
Project-URL: Documentation, https://github.com/ctoicqtao/mcp-veo3-azure-blob/blob/main/README.md
Project-URL: Bug Tracker, https://github.com/ctoicqtao/mcp-veo3-azure-blob/issues
Project-URL: Changelog, https://github.com/ctoicqtao/mcp-veo3-azure-blob/releases
Author-email: Tom Chen <ctoicqtao@gmail.com>
Maintainer-email: Tom Chen <ctoicqtao@gmail.com>
License: MIT
License-File: LICENSE
Keywords: ai,fastmcp,gemini,generation,google,mcp,model-context-protocol,veo,video
Classifier: Development Status :: 4 - Beta
Classifier: Intended Audience :: Developers
Classifier: License :: OSI Approved :: MIT License
Classifier: Operating System :: OS Independent
Classifier: Programming Language :: Python :: 3
Classifier: Programming Language :: Python :: 3.10
Classifier: Programming Language :: Python :: 3.11
Classifier: Programming Language :: Python :: 3.12
Classifier: Topic :: Internet :: WWW/HTTP :: HTTP Servers
Classifier: Topic :: Multimedia :: Video
Classifier: Topic :: Scientific/Engineering :: Artificial Intelligence
Classifier: Topic :: Software Development :: Libraries :: Python Modules
Requires-Python: >=3.10
Requires-Dist: aiohttp>=3.8.0
Requires-Dist: azure-storage-blob>=12.19.0
Requires-Dist: fastmcp>=2.11.0
Requires-Dist: google-genai>=0.3.0
Requires-Dist: pillow>=10.0.0
Requires-Dist: pydantic>=2.11.0
Requires-Dist: python-dotenv>=1.1.0
